pypz/sniffer/__init__.py
pypz/sniffer/__main__.py
pypz/sniffer/sniffer.py
pypz/sniffer/utils.py
pypz/sniffer/viewer.py
pypz/sniffer/views.py
pypz_io_sniffer-0.9.5.dist-info/licenses/LICENSE
pypz_io_sniffer-0.9.5.dist-info/METADATA
pypz_io_sniffer-0.9.5.dist-info/WHEEL
pypz_io_sniffer-0.9.5.dist-info/top_level.txt
pypz_io_sniffer-0.9.5.dist-info/RECORD
