Metadata-Version: 2.4
Name: pypz-io-sniffer
Version: 0.9.5
Summary: A small tool that is capable to sniff and visualize the control messages between Operators.
Author-email: Laszlo Anka <laszlo.anka@gmail.com>
License: Apache-2.0
Project-URL: Documentation, https://pypz.dev
Project-URL: Repository, https://github.com/lazlowa/pypz-python
Keywords: pypz,sniffer
Classifier: Natural Language :: English
Classifier: Operating System :: OS Independent
Classifier: Programming Language :: Python :: 3.11
Requires-Python: >=3.11
License-File: LICENSE
Requires-Dist: pypz-core
Provides-Extra: static
Requires-Dist: flake8~=7.0.0; extra == "static"
Requires-Dist: flake8-html~=0.4.3; extra == "static"
Requires-Dist: mypy~=1.8.0; extra == "static"
Requires-Dist: coverage~=7.4.1; extra == "static"
Dynamic: license-file
